{
    "atd_music_search_api": {
        "secret": "your-secret-here"
    },
    "spotify": {
        "auth_url": "https://accounts.spotify.com/api",
        "api_url": "https://api.spotify.com/v1",
        "client_id": "your-client-id-here",
        "client_secret": "your-client-secret-here"
    },
    "tidal": {
        "auth_url": "https://auth.tidal.com/v1",
        "api_url": "https://openapi.tidal.com",
        "client_id": "your-client-id-here",
        "client_secret": "your-client-secret-here"
    },
    "youtube": {
        "api_url": "https://www.googleapis.com/youtube/v3",
        "api_key": "your-api-key-here"
    },
    "deezer": {
        "auth_url": "https://connect.deezer.com/oauth/access_token.php",
        "api_url": "https://api.deezer.com",
        "client_id": "your-client-id-here",
        "client_secret": "your-client-secret-here"
    },
    "genius": {
        "api_url": "https://api.genius.com",
        "client_id": "your-client-id-here",
        "client_secret": "your-client-secret-here"
    }
}
